[
  {
    "index": 10010101,
    "id": "9e3e3994-a3ed-47ca-as014-d4483884cfe2",
    "featuredImage": "",
    "title": "",
    "desc": "",
    "date": "",
    "href": "",
    "commentCount": null,
    "viewdCount": null,
    "readingTime": "",
    "bookmark": { "count": null, "isBookmarked": "" },
    "like": { "count": null, "isLiked": "" },
    "authorId": 4,
    "categoriesId": [3],
    "postType": "gallery",
    "galleryImgs": [
      "",
      "",
      "",
      "",
      ""
    ]
  },
  {
    "index": 21001,
    "id": "af92a665-4a4d-4cff-9e17-89456dfs21fb5",
    "featuredImage": "",
    "title": "",
    "desc": "",
    "date": "",
    "href": "",
    "commentCount": null,
    "viewdCount": null,
    "readingTime": "",
    "bookmark": { "count": null, "isBookmarked": "" },
    "like": { "count": null, "isLiked": "" },
    "authorId": 4,
    "categoriesId": [3],
    "postType": "gallery",
    "galleryImgs": [
      "",
      "",
      "",
      "",
      ""
    ]
  },
  {
    "index": 31002,
    "id": "dffe0224-ebff-4803-bb66-e8dd128656284",
    "featuredImage": "",
    "title": "",
    "desc": "",
    "date": "",
    "href": "",
    "commentCount": null,
    "viewdCount": null,
    "readingTime": "",
    "bookmark": { "count": null, "isBookmarked": "" },
    "like": { "count": null, "isLiked": "" },
    "authorId": 4,
    "categoriesId": [3],
    "postType": "gallery",
    "galleryImgs": [
      "",
      "",
      "",
      "",
      ""
    ]
  },
  {
    "index": 41001,
    "id": "5ac7cb90-4694-42e8-8883-16372f711eaa8",
    "featuredImage": "",
    "title": "",
    "desc": "",
    "date": "",
    "href": "",
    "commentCount": null,
    "viewdCount": null,
    "readingTime": "",
    "bookmark": { "count": null, "isBookmarked": "" },
    "like": { "count": null, "isLiked": "" },
    "authorId": 4,
    "categoriesId": [3],
    "postType": "gallery",
    "galleryImgs": [
      "",
      "",
      "",
      "",
      ""
    ]
  },
  {
    "index": 51002,
    "id": "f82a8455-3a14-4af9-b6d2-ac6cd74e0d07c",
    "featuredImage": "",
    "title": "",
    "desc": "",
    "date": "",
    "href": "",
    "commentCount": null,
    "viewdCount": null,
    "readingTime": "",
    "bookmark": { "count": null, "isBookmarked": "" },
    "like": { "count": null, "isLiked": "" },
    "authorId": 4,
    "categoriesId": [3],
    "postType": "gallery",
    "galleryImgs": [
      "",
      "",
      "",
      "",
      ""
    ]
  },
  {
    "index": 61002,
    "id": "54c11c92-049f-4353-8cdb-f7fsec70d3ae75",
    "featuredImage": "",
    "title": "",
    "desc": "",
    "date": "",
    "href": "",
    "commentCount": null,
    "viewdCount": null,
    "readingTime": "",
    "bookmark": { "count": null, "isBookmarked": "" },
    "like": { "count": null, "isLiked": "" },
    "authorId": 4,
    "categoriesId": [3],
    "postType": "gallery",
    "galleryImgs": [
      "",
      "",
      "",
      "",
      ""
    ]
  },
  {
    "index": 71003,
    "id": "1c40aaaf-0077-4f54-9b34-fse90d95e17c7e",
   "featuredImage": "",
    "title": "",
    "desc": "",
    "date": "",
    "href": "",
    "commentCount": null,
    "viewdCount": null,
    "readingTime": "",
    "bookmark": { "count": null, "isBookmarked": "" },
    "like": { "count": null, "isLiked": "" },
    "authorId": 4,
    "categoriesId": [3],
    "postType": "gallery",
    "galleryImgs": [
      "",
      "",
      "",
      "",
      ""
    ]
  },
  {
    "index": 810001,
    "id": "9f1739eb-8f00-4c99-97fsf4-63544b6a2d12",
    "featuredImage": "",
    "title": "",
    "desc": "",
    "date": "",
    "href": "",
    "commentCount": null,
    "viewdCount": null,
    "readingTime": "",
    "bookmark": { "count": null, "isBookmarked": "" },
    "like": { "count": null, "isLiked": "" },
    "authorId": 4,
    "categoriesId": [3],
    "postType": "gallery",
    "galleryImgs": [
      "",
      "",
      "",
      "",
      ""
    ]
  },
  {
    "index": 910002,
    "id": "0991ab0b-696f-4d7f-afe7-9c624fsfseb8c050",
    "featuredImage": "",
    "title": "",
    "desc": "",
    "date": "",
    "href": "",
    "commentCount": null,
    "viewdCount": null,
    "readingTime": "",
    "bookmark": { "count": null, "isBookmarked": "" },
    "like": { "count": null, "isLiked": "" },
    "authorId": 4,
    "categoriesId": [3],
    "postType": "gallery",
    "galleryImgs": [
      "",
      "",
      "",
      "",
      ""
    ]
  },
  {
    "index": 1010101,
    "id": "eae0e85d-db11-44fa-ac32-6c192ffsf687e0c",
    "featuredImage": "",
    "title": "",
    "desc": "",
    "date": "",
    "href": "",
    "commentCount": null,
    "viewdCount": null,
    "readingTime": "",
    "bookmark": { "count": null, "isBookmarked": "" },
    "like": { "count": null, "isLiked": "" },
    "authorId": 4,
    "categoriesId": [3],
    "postType": "gallery",
    "galleryImgs": [
      "",
      "",
      "",
      "",
      ""
    ]
  },
  {
    "index": 1110101,
    "id": "10f85e8a-a75a-485a-a1af-75551fsfs93fae1a",
    "featuredImage": "",
    "title": "",
    "desc": "",
    "date": "",
    "href": "",
    "commentCount": null,
    "viewdCount": null,
    "readingTime": "",
    "bookmark": { "count": null, "isBookmarked": "" },
    "like": { "count": null, "isLiked": "" },
    "authorId": 4,
    "categoriesId": [3],
    "postType": "gallery",
    "galleryImgs": [
      "",
      "",
      "",
      "",
      ""
    ]
  },
  {
    "index": 1210101,
    "id": "f924ccfb-2622-497d-8072-fsfsfsdf373c73cbaa",
    "featuredImage": "",
    "title": "",
    "desc": "",
    "date": "",
    "href": "",
    "commentCount": null,
    "viewdCount": null,
    "readingTime": "",
    "bookmark": { "count": null, "isBookmarked": "" },
    "like": { "count": null, "isLiked": "" },
    "authorId": 4,
    "categoriesId": [3],
    "postType": "gallery",
    "galleryImgs": [
      "",
      "",
      "",
      ""
    ]
  },
  {
    "index": 13111222,
    "id": "6fa9d0b2-d48b-48f3-b862-cb38a4bsss6c755",
    "featuredImage": "",
    "title": "",
    "desc": "",
    "date": "",
    "href": "",
    "commentCount": null,
    "viewdCount": null,
    "readingTime": "",
    "bookmark": { "count": null, "isBookmarked": "" },
    "like": { "count": null, "isLiked": "" },
    "authorId": 4,
    "categoriesId": [3],
    "postType": "gallery",
    "galleryImgs": [
      "",
      "",
      "",
      ""
    ]
  },
  {
    "index": 1410101,
    "id": "95de5119-776e-4c7f-9ff3-fsfsfs52482f9a2081",
    "featuredImage": "",
    "title": "",
    "desc": "",
    "date": "",
    "href": "",
    "commentCount": null,
    "viewdCount": null,
    "readingTime": "",
    "bookmark": { "count": null, "isBookmarked": "" },
    "like": { "count": null, "isLiked": "" },
    "authorId": 4,
    "categoriesId": [3],
    "postType": "gallery",
    "galleryImgs": [
      "",
      "",
      "",
      "",
      ""
    ]
  },
  {
    "index": 151010101,
    "id": "499ea541-5d70-4978-81111b41-eeb3987024bd",
    "featuredImage": "",
    "title": "",
    "desc": "",
    "date": "",
    "href": "",
    "commentCount": null,
    "viewdCount": null,
    "readingTime": "",
    "bookmark": { "count": null, "isBookmarked": "" },
    "like": { "count": null, "isLiked": "" },
    "authorId": 4,
    "categoriesId": [3],
    "postType": "gallery",
    "galleryImgs": [
      "",
      "",
      "",
      ""
    ]
  },
  {
    "index": 16101010111,
    "id": "20992b33-1bae-4867-b11110fb-dec76ac1e0da",
    "featuredImage": "",
    "title": "",
    "desc": "",
    "date": "",
    "href": "",
    "commentCount": null,
    "viewdCount": null,
    "readingTime": "",
    "bookmark": { "count": null, "isBookmarked": "" },
    "like": { "count": null, "isLiked": "" },
    "authorId": 4,
    "categoriesId": [3],
    "postType": "gallery",
    "galleryImgs": [
      "",
      "",
      "",
      ""
    ]
  },
  {
    "index": 17101011,
    "id": "71fde139-b111176-44e3-8514-2296f1d888d3",
    "featuredImage": "",
    "title": "",
    "desc": "",
    "date": "",
    "href": "",
    "commentCount": null,
    "viewdCount": null,
    "readingTime": "",
    "bookmark": { "count": null, "isBookmarked": "" },
    "like": { "count": null, "isLiked": "" },
    "authorId": 4,
    "categoriesId": [3],
    "postType": "gallery",
    "galleryImgs": [
      "",
      "",
      "",
      ""
    ]
  },
  {
    "index": 181101011,
    "id": "f63fbb28-94a6-4a87-bfe4-5111ac6a9e7990b",
    "featuredImage": "",
    "title": "",
    "desc": "",
    "date": "",
    "href": "",
    "commentCount": null,
    "viewdCount": null,
    "readingTime": "",
    "bookmark": { "count": null, "isBookmarked": "" },
    "like": { "count": null, "isLiked": "" },
    "authorId": 4,
    "categoriesId": [3],
    "postType": "gallery",
    "galleryImgs": [
      "",
      "",
      "",
      ""
    ]
  },
  {
    "index": 19191919,
    "id": "2980bc99111-74c7-4507-a28d-78966ec71acf",
    "featuredImage": "",
    "title": "",
    "desc": "",
    "date": "",
    "href": "",
    "commentCount": null,
    "viewdCount": null,
    "readingTime": "",
    "bookmark": { "count": null, "isBookmarked": "" },
    "like": { "count": null, "isLiked": "" },
    "authorId": 4,
    "categoriesId": [3],
    "postType": "gallery",
    "galleryImgs": [
      "",
      "",
      "",
      ""
    ]
  },
  {
    "index": 20100111,
    "id": "c8f8e679-d434-4a1111c-9448-efc44814d11e",
    "featuredImage": "",
    "title": "",
    "desc": "",
    "date": "",
    "href": "",
    "commentCount": null,
    "viewdCount": null,
    "readingTime": "",
    "bookmark": { "count": null, "isBookmarked": "" },
    "like": { "count": null, "isLiked": "" },
    "authorId": 4,
    "categoriesId": [3],
    "postType": "gallery",
    "galleryImgs": [
      "",
      "",
      "",
      ""
    ]
  },
  {
    "index": 2101010111,
    "id": "293b349d-5112-4eb4-a28b-5db8dbd511111aed",
    "featuredImage": "",
    "title": "",
    "desc": "",
    "date": "",
    "href": "",
    "commentCount": null,
    "viewdCount": null,
    "readingTime": "",
    "bookmark": { "count": null, "isBookmarked": "" },
    "like": { "count": null, "isLiked": "" },
    "authorId": 4,
    "categoriesId": [3],
    "postType": "gallery",
    "galleryImgs": [
      "",
      "",
      "",
      ""
    ]
  },
  {
    "index": 2201010101,
    "id": "fa96a568-e4ce1111-4beb-a2ac-120a164e0e4a",
    "featuredImage": "",
    "title": "",
    "desc": "",
    "date": "",
    "href": "",
    "commentCount": null,
    "viewdCount": null,
    "readingTime": "",
    "bookmark": { "count": null, "isBookmarked": "" },
    "like": { "count": null, "isLiked": "" },
    "authorId": 4,
    "categoriesId": [3],
    "postType": "gallery",
    "galleryImgs": [
      "",
      "",
      "",
      ""
    ]
  },
  {
    "index": 2301010011,
    "id": "0e48196f-644b-46d4-99f8-9ece6761218c",
    "featuredImage": "",
    "title": "",
    "desc": "",
    "date": "",
    "href": "",
    "commentCount": null,
    "viewdCount": null,
    "readingTime": "",
    "bookmark": { "count": null, "isBookmarked": "" },
    "like": { "count": null, "isLiked": "" },
    "authorId": 4,
    "categoriesId": [3],
    "postType": "gallery",
    "galleryImgs": [
      "",
      "",
      "",
      ""
    ]
  }
]
